binapy/__init__.py
binapy/binapy.py
binapy/compression/__init__.py
binapy/compression/zlib.py
binapy/encoding/__init__.py
binapy/encoding/base64.py
binapy/encoding/hex.py
binapy/encoding/url.py
binapy/hashing/__init__.py
binapy/hashing/sha.py
binapy/hashing/shake.py
binapy/parsing/__init__.py
binapy/parsing/json.py
binapy/py.typed
binapy-0.6.1.dist-info/LICENSE
binapy-0.6.1.dist-info/METADATA
binapy-0.6.1.dist-info/WHEEL
binapy-0.6.1.dist-info/RECORD
