Metadata-Version: 2.1
Name: binapy
Version: 0.6.1
Summary: Binary Data manipulation, for humans.
Home-page: https://github.com/guillp/binapy
License: MIT
Author: Guillaume Pujol
Author-email: guill.p.linux@gmail.com
Requires-Python: >=3.7,<4.0
Classifier: Development Status :: 2 - Pre-Alpha
Classifier: Intended Audience :: Developers
Classifier: License :: OSI Approved :: MIT License
Classifier: Natural Language :: English
Classifier: Programming Language :: Python :: 3
Classifier: Programming Language :: Python :: 3.7
Classifier: Programming Language :: Python :: 3.8
Classifier: Programming Language :: Python :: 3.9
Classifier: Programming Language :: Python :: 3.10
Classifier: Programming Language :: Python :: 3.11
Requires-Dist: typing-extensions (>=4.3.0,<5.0.0)
